README.md
setup.py
benchmol/__init__.py
benchmol.egg-info/PKG-INFO
benchmol.egg-info/SOURCES.txt
benchmol.egg-info/dependency_links.txt
benchmol.egg-info/top_level.txt
benchmol/configs/StructureNet_params.py
benchmol/configs/__init__.py
benchmol/configs/model_params.py
benchmol/data_process/__init__.py
benchmol/data_process/molecules/__init__.py
benchmol/data_process/molecules/fingerprints.py
benchmol/data_process/molecules/generate_3d_graph_data_from_csv.py
benchmol/data_process/molecules/generate_3d_images_pymol.py
benchmol/data_process/molecules/generate_StructureNet.py
benchmol/data_process/molecules/generate_graph_data_from_csv.py
benchmol/data_process/molecules/generate_images_rdkit.py
benchmol/data_process/molecules/get_fp_features.py
benchmol/data_process/molecules/geometry_helpers/__init__.py
benchmol/data_process/molecules/geometry_helpers/data_utils.py
benchmol/data_process/molecules/graph_helpers/__init__.py
benchmol/data_process/molecules/graph_helpers/mol2_3dgraph.py
benchmol/data_process/molecules/graph_helpers/mol2graph.py
benchmol/data_process/molecules/ogb_helpers/__init__.py
benchmol/data_process/molecules/ogb_helpers/mol.py
benchmol/data_process/molecules/ogb_helpers/mol_sdf2_3dgraph.py
benchmol/dataloader/__init__.py
benchmol/dataloader/collater.py
benchmol/dataloader/data_utils.py
benchmol/dataloader/feat_dataset.py
benchmol/dataloader/geometry_dataset.py
benchmol/dataloader/graph_dataset.py
benchmol/dataloader/image_dataset.py
benchmol/dataloader/sequence_dataset.py
benchmol/feature_extraction/__init__.py
benchmol/feature_extraction/feature_extractor.py
benchmol/metrics/__init__.py
benchmol/metrics/metric.py
benchmol/model_pools/__init__.py
benchmol/model_pools/base_utils.py
benchmol/model_pools/geometry_factory.py
benchmol/model_pools/graph_factory.py
benchmol/model_pools/image_factory.py
benchmol/model_pools/smiles_factory.py
benchmol/model_pools/geom3d/AWARE.py
benchmol/model_pools/geom3d/AutoEncoder.py
benchmol/model_pools/geom3d/BERT.py
benchmol/model_pools/geom3d/CDConv.py
benchmol/model_pools/geom3d/CNN.py
benchmol/model_pools/geom3d/ClofNet.py
