Metadata-Version: 2.1
Name: benchmol
Version: 0.0.2
Summary: A Multi-Modality Benchmarking Platform For Molecular Representation
Home-page: https://github.com/HongxinXiang/BenchMol
Author: Hongxin Xiang
Author-email: 
Keywords: python,pytorch,benchmol,multi-modality platform,molecular representation learning
Classifier: Programming Language :: Python :: 3
Classifier: Development Status :: 5 - Production/Stable
Classifier: Intended Audience :: Developers
Classifier: Operating System :: OS Independent
Classifier: Operating System :: Unix
Classifier: Operating System :: MacOS :: MacOS X
Classifier: Operating System :: Microsoft :: Windows
Classifier: License :: OSI Approved :: MIT License
Requires-Python: >=3.0
